{
    "type": ["null", "object"],
    "additionalProperties": false,
    "properties": {
        "study_id": {"type": "string"},
        "study_name": {"type": "string"},
        "study_description": {"type": "string"},
        "study_start_time": {"type": "string", "format": "date-time"},
        "study_end_time": {"type": "string", "format": "date-time"},
        "objective_id": {"type": "string"},
        "objective_name": {"type": "string"},
        "objective_type": {"type": "string"},
        "objective_is_primary": {"type": "boolean"},
        "objective_last_updated_results": {"type": "string", "format": "date"},
        "result_population_test": {"type": ["null", "integer"]},
        "result_population_control": {"type": ["null", "integer"]},
        "result_population_reached": {"type": ["null", "integer"]},
        "result_impressions": {"type": ["null", "integer"]},
        "result_spend": {"type": ["null", "number"]},
        "result_frequency": {"type": ["null", "number"]},
        "result_buyers_test": {"type": ["null", "integer"]},
        "result_buyers_control": {"type": ["null", "integer"]},
        "result_buyers_scaled": {"type": ["null", "number"]},
        "result_buyers_incremental": {"type": ["null", "number"]},
        "result_buyers_reached": {"type": ["null", "integer"]},
        "result_buyers_reachedPercent": {"type": ["null", "number"]},
        "result_buyers_baseline": {"type": ["null", "number"]},
        "result_buyers_lift": {"type": ["null", "number"]},
        "result_buyers_delta": {"type": ["null", "number"]},
        "result_buyers_pValue": {"type": ["null", "number"]},
        "result_buyers_isStatSig":{"type": ["null", "integer"]}, 
        "result_conversions_test": {"type": ["null", "integer"]},
        "result_conversions_control": {"type": ["null", "integer"]},
        "result_conversions_scaled": {"type": ["null", "number"]},
        "result_conversions_incremental": {"type": ["null", "number"]},
        "result_conversions_reached": {"type": ["null", "integer"]},
        "result_conversions_reachedPercent": {"type": ["null", "number"]},
        "result_conversions_baseline": {"type": ["null", "number"]},
        "result_conversions_lift": {"type": ["null", "number"]},
        "result_conversions_delta": {"type": ["null", "number"]},
        "result_conversions_pValue": {"type": ["null", "number"]},
        "result_conversions_isStatSig":{"type": ["null", "integer"]},
        "result_advancedConversions_test": {"type": ["null", "integer"]},
        "result_advancedConversions_control": {"type": ["null", "integer"]},
        "result_advancedConversions_scaled": {"type": ["null", "number"]},
        "result_advancedConversions_incremental": {"type": ["null", "number"]},
        "result_advancedConversions_baseline": {"type": ["null", "number"]},
        "result_advancedConversions_lift": {"type": ["null", "number"]},
        "result_advancedConversions_informativeSingleCellBayesianConfidence": {"type": ["null", "number"]},
        "result_advancedConversions_informativeMultiCellBayesianConfidence": {"type": ["null", "number"]},
        "result_advancedConversions_bayesianCILower": {"type": ["null", "number"]},
        "result_advancedConversions_bayesianCIUpper": {"type": ["null", "number"]},
        "age": {"type": ["null", "integer"]},
        "gender": {"type": ["null", "integer"]},
        "cell_id": {"type": ["null", "integer"]},
        "country": {"type": ["null", "integer"]}
    }
}
